main.py
toronto_open_data_mcp_server-0.2.0.dist-info/licenses/LICENSE
toronto_open_data_mcp_server-0.2.0.dist-info/METADATA
toronto_open_data_mcp_server-0.2.0.dist-info/WHEEL
toronto_open_data_mcp_server-0.2.0.dist-info/entry_points.txt
toronto_open_data_mcp_server-0.2.0.dist-info/top_level.txt
toronto_open_data_mcp_server-0.2.0.dist-info/RECORD
