Metadata-Version: 2.4
Name: toronto-open-data-mcp-server
Version: 0.2.0
Summary: MCP server for accessing Toronto Open Data through the CKAN API
Author: Vince Duquette
License-Expression: MIT
Project-URL: Homepage, https://github.com/yourusername/toronto-open-data-mcp-server
Project-URL: Bug Reports, https://github.com/yourusername/toronto-open-data-mcp-server/issues
Project-URL: Source, https://github.com/yourusername/toronto-open-data-mcp-server
Keywords: mcp,toronto,open-data,ckan,api
Classifier: Development Status :: 4 - Beta
Classifier: Intended Audience :: Developers
Classifier: Programming Language :: Python :: 3
Classifier: Programming Language :: Python :: 3.10
Classifier: Programming Language :: Python :: 3.11
Classifier: Programming Language :: Python :: 3.12
Requires-Python: >=3.10
License-File: LICENSE
Requires-Dist: mcp[cli]>=1.9.0
Provides-Extra: test
Requires-Dist: pytest>=7.0.0; extra == "test"
Requires-Dist: pytest-cov>=4.0.0; extra == "test"
Requires-Dist: pytest-mock>=3.0.0; extra == "test"
Dynamic: license-file
